{
  "version": 1,
  "topic": {
    "slug": "string",
    "name": "String"
  },
  "updatedAt": "2026-06-22T07:19:18.312Z",
  "problems": [
    {
      "frontendId": "412",
      "title": "Fizz Buzz",
      "slug": "fizz-buzz",
      "problemName": "0412-fizz-buzz",
      "difficulty": "Easy",
      "leetcodeUrl": "https://leetcode.com/problems/fizz-buzz/",
      "folderPath": "0412-fizz-buzz/",
      "readmePath": "0412-fizz-buzz/README.md",
      "solutions": [
        {
          "language": "C++",
          "extension": ".cpp",
          "filename": "0412-fizz-buzz.cpp",
          "path": "0412-fizz-buzz/0412-fizz-buzz.cpp",
          "sha": "9e82e4c8858fed6a04da534f630cd3346d3820e8",
          "lastSyncedAt": "2026-06-22T07:19:18.312Z"
        }
      ]
    }
  ]
}
